erosolar/__init__.py
erosolar/__main__.py
erosolar/app.py
erosolar/agent_system/__init__.py
erosolar/agent_system/embeddings_agent.py
erosolar/agent_system/embeddings_router.py
erosolar/agent_system/enhanced_tool_registry.py
erosolar/agent_system/langgraph_agent.py
erosolar/agent_system/router.py
erosolar/agent_system/router_deprecated.py
erosolar/agent_system/router_old.py
erosolar/agent_system/tool_registry.py
erosolar/agent_system/true_react_agent.py
erosolar/agent_system/vector_store.py
erosolar/agent_system/tools/open_metro_weather.py
erosolar/agent_system/tools/tavily.py
erosolar-1.0.0.dist-info/licenses/LICENSE
erosolar-1.0.0.dist-info/METADATA
erosolar-1.0.0.dist-info/WHEEL
erosolar-1.0.0.dist-info/entry_points.txt
erosolar-1.0.0.dist-info/top_level.txt
erosolar-1.0.0.dist-info/RECORD
