Metadata-Version: 2.4
Name: erosolar
Version: 1.0.0
Summary: AI-powered chat interface with DeepSeek, featuring tool integrations and embeddings
Author-email: ErosolarAI <noreply@erosolar.ai>
Maintainer-email: ErosolarAI <noreply@erosolar.ai>
License: MIT
Project-URL: Homepage, https://pypi.org/project/erosolar/
Project-URL: Repository, https://github.com/ErosolarAI/erosolar-pypi
Project-URL: Issues, https://github.com/ErosolarAI/erosolar-pypi/issues
Project-URL: Documentation, https://github.com/ErosolarAI/erosolar-pypi/blob/main/README.md
Keywords: ai,chatbot,deepseek,openai,embeddings,flask,web,assistant
Classifier: Development Status :: 3 - Alpha
Classifier: Intended Audience :: Developers
Classifier: Intended Audience :: Science/Research
Classifier: License :: OSI Approved :: MIT License
Classifier: Operating System :: OS Independent
Classifier: Programming Language :: Python :: 3
Classifier: Programming Language :: Python :: 3.8
Classifier: Programming Language :: Python :: 3.9
Classifier: Programming Language :: Python :: 3.10
Classifier: Programming Language :: Python :: 3.11
Classifier: Programming Language :: Python :: 3.12
Classifier: Topic :: Scientific/Engineering :: Artificial Intelligence
Classifier: Topic :: Software Development :: Libraries :: Python Modules
Requires-Python: >=3.8
License-File: LICENSE
Requires-Dist: flask>=2.0.0
Requires-Dist: openai>=1.0.0
Requires-Dist: requests>=2.25.0
Requires-Dist: numpy>=1.20.0
Provides-Extra: langgraph
Requires-Dist: langgraph>=0.1.0; extra == "langgraph"
Provides-Extra: dev
Requires-Dist: pytest>=7.0.0; extra == "dev"
Requires-Dist: black>=22.0.0; extra == "dev"
Requires-Dist: flake8>=4.0.0; extra == "dev"
Requires-Dist: mypy>=0.950; extra == "dev"
Dynamic: license-file
